saline_sdk/__init__.py
saline_sdk/account.py
saline_sdk/crypto/__init__.py
saline_sdk/crypto/bls.py
saline_sdk/crypto/key_derivation.py
saline_sdk/rpc/__init__.py
saline_sdk/rpc/client.py
saline_sdk/rpc/error.py
saline_sdk/rpc/query_responses.py
saline_sdk/rpc/testnet/__init__.py
saline_sdk/rpc/testnet/faucet.py
saline_sdk/transaction/__init__.py
saline_sdk/transaction/bindings.py
saline_sdk/transaction/bindings_docstrings.py
saline_sdk/transaction/instructions.py
saline_sdk/transaction/serialisation.py
saline_sdk/transaction/tx.py
saline_sdk-0.2.2.dist-info/LICENSE.txt
saline_sdk-0.2.2.dist-info/METADATA
saline_sdk-0.2.2.dist-info/WHEEL
saline_sdk-0.2.2.dist-info/RECORD
