Metadata-Version: 2.3
Name: saline-sdk
Version: 0.2.2
Summary: Official SDK for interacting with the Saline blockchain network
License: MIT
Keywords: blockchain,cryptocurrency,saline,web3
Author: Rising Sea Labs
Author-email: info@risingsealabs.com
Requires-Python: >=3.12,<3.13
Classifier: Development Status :: 4 - Beta
Classifier: Intended Audience :: Developers
Classifier: License :: OSI Approved :: MIT License
Classifier: Programming Language :: Python :: 3.12
Classifier: Topic :: Software Development :: Libraries :: Python Modules
Requires-Dist: aiohttp (>=3.9.3)
Requires-Dist: bitstring (>=4.3.0)
Requires-Dist: blspy (>=2.0.3)
Requires-Dist: httpx (>=0.28.1)
Requires-Dist: mnemonic (>=0.21)
Requires-Dist: myst-parser (>=2.0.0)
Requires-Dist: numpy (>=2.2.4)
Requires-Dist: requests (>=2.32.3)
Requires-Dist: sphinx (>=7.2.6)
Requires-Dist: sphinx-autodoc-typehints (>=2.0.0)
Requires-Dist: sphinx-rtd-theme (>=2.0.0)
Requires-Dist: websockets (>=14.2)
Project-URL: Bug Tracker, https://github.com/risingsealabs/saline-sdk/issues
Project-URL: Documentation, https://saline-sdk.readthedocs.com
Project-URL: Homepage, https://github.com/risingsealabs/saline-sdk
